LICENSE
NOTICE
README.md
datapane_components/README.md
datapane_components/__init__.py
datapane_components/calendar_heatmap.py
datapane_components/chatgpt.py
datapane_components/datasets.py
datapane_components/timeline.py
datapane_components/utils.py
datapane_components-2023.3.20.dist-info/LICENSE
datapane_components-2023.3.20.dist-info/METADATA
datapane_components-2023.3.20.dist-info/WHEEL
datapane_components-2023.3.20.dist-info/RECORD
