Metadata-Version: 2.1
Name: datapane-components
Version: 2023.3.20
Summary: Reusable Datapane components and sample reports and apps
Home-page: https://www.datapane.com
License: Apache 2.0
Keywords: data,analysis,jupyter,pandas,altair
Author: Datapane Team
Author-email: dev@datapane.com
Requires-Python: >=3.8.0,<3.12.0
Classifier: Development Status :: 2 - Pre-Alpha
Classifier: Environment :: Console
Classifier: Intended Audience :: Developers
Classifier: License :: OSI Approved :: Apache Software License
Classifier: License :: Other/Proprietary License
Classifier: Natural Language :: English
Classifier: Operating System :: OS Independent
Classifier: Programming Language :: Python :: 3
Classifier: Programming Language :: Python :: 3.8
Classifier: Programming Language :: Python :: 3.9
Classifier: Programming Language :: Python :: 3.10
Classifier: Programming Language :: Python :: 3.11
Classifier: Topic :: Software Development
Classifier: Topic :: Software Development :: Libraries :: Python Modules
Requires-Dist: altair (>=4.0.0,<5.0.0)
Requires-Dist: datapane (>=0.16.1,<0.17.0)
Requires-Dist: duckdb (>=0.7.1,<0.8.0)
Requires-Dist: openai (>=0.27.0,<0.28.0)
Requires-Dist: pooch (>=1.6.0,<2.0.0)
Requires-Dist: vega-datasets (>=0.9.0,<1.0.0)
Project-URL: Documentation, https://docs.datapane.com
Project-URL: Repository, https://github.com/datapane/datapane
